[{"competition":"AFF Championship: Group A","home":"Philippines","away":"Indonesia","homeScore":"1","HomeScoreInt":1,"awayScore":"2","awayScoreInt":2},{"competition":"AFF Championship: Group A","home":"Thailand","away":"Cambodia","homeScore":"3","HomeScoreInt":3,"awayScore":"1","awayScoreInt":1},{"competition":"A-League 22/23","home":"Wellington Phoenix","away":"Melbourne City FC","homeScore":"1","HomeScoreInt":1,"awayScore":"3","awayScoreInt":3},{"competition":"A-League 22/23","home":"Adelaide United","away":"Perth Glory","homeScore":"2","HomeScoreInt":2,"awayScore":"0","awayScoreInt":0},{"competition":"Premier League 22/23","home":"Brentford","away":"Liverpool","homeScore":"3","HomeScoreInt":3,"awayScore":"1","awayScoreInt":1},{"competition":"Championship 22/23","home":"Birmingham City","away":"Middlesbrough","homeScore":"1","HomeScoreInt":1,"awayScore":"3","awayScoreInt":3},{"competition":"Championship 22/23","home":"Norwich City","away":"Watford","homeScore":"0","HomeScoreInt":0,"awayScore":"1","awayScoreInt":1},{"competition":"Championship 22/23","home":"Swansea City","away":"Burnley","homeScore":"1","HomeScoreInt":1,"awayScore":"2","awayScoreInt":2},{"competition":"Championship 22/23","home":"West Bromwich Albion","away":"Reading","homeScore":"1","HomeScoreInt":1,"awayScore":"0","awayScoreInt":0},{"competition":"Championship 22/23","home":"Wigan Athletic","away":"Hull City","homeScore":"1","HomeScoreInt":1,"awayScore":"4","awayScoreInt":4},{"competition":"Championship 22/23","home":"Stoke City","away":"Preston North End","homeScore":"0","HomeScoreInt":0,"awayScore":"1","awayScoreInt":1},{"competition":"Championship 22/23","home":"Queens Park Rangers","away":"Sheffield United","homeScore":"1","HomeScoreInt":1,"awayScore":"1","awayScoreInt":1},{"competition":"League 1 22/23","home":"Barnsley","away":"Bolton Wanderers","homeScore":"0","HomeScoreInt":0,"awayScore":"3","awayScoreInt":3},{"competition":"League 1 22/23","home":"Derby County","away":"Accrington Stanley","homeScore":"4","HomeScoreInt":4,"awayScore":"0","awayScoreInt":0},{"competition":"League 1 22/23","home":"Lincoln City","away":"Ipswich Town","homeScore":"1","HomeScoreInt":1,"awayScore":"1","awayScoreInt":1},{"competition":"League 1 22/23","home":"Sheffield Wednesday","away":"Cambridge United","homeScore":"5","HomeScoreInt":5,"awayScore":"0","awayScoreInt":0},{"competition":"League 2 22/23","home":"Barrow","away":"Rochdale","homeScore":"0","HomeScoreInt":0,"awayScore":"0","awayScoreInt":0},{"competition":"League 2 22/23","home":"Newport County","away":"Crawley Town","homeScore":"2","HomeScoreInt":2,"awayScore":"2","awayScoreInt":2},{"competition":"League 2 22/23","home":"Northampton Town","away":"Leyton Orient","homeScore":"1","HomeScoreInt":1,"awayScore":"0","awayScoreInt":0},{"competition":"League 2 22/23","home":"Stevenage","away":"Gillingham","homeScore":"1","HomeScoreInt":1,"awayScore":"0","awayScoreInt":0},{"competition":"Ligue 1 22/23","home":"Strasbourg","away":"Troyes","homeScore":"2","HomeScoreInt":2,"awayScore":"3","awayScoreInt":3},{"competition":"Ligue 1 22/23","home":"Lille","away":"Reims","homeScore":"1","HomeScoreInt":1,"awayScore":"1","awayScoreInt":1},{"competition":"Ligue 1 22/23","home":"Montpellier","away":"Marseille","homeScore":"1","HomeScoreInt":1,"awayScore":"2","awayScoreInt":2},{"competition":"Ligue 1 22/23","home":"Rennes","away":"Nice","homeScore":"2","HomeScoreInt":2,"awayScore":"1","awayScoreInt":1},{"competition":"Liga Leumit 22/23","home":"Hapoel Ironi Akko","away":"Hapoel Umm al-Fahm","homeScore":"0","HomeScoreInt":0,"awayScore":"1","awayScoreInt":1},{"competition":"Liga Leumit 22/23","home":"Hapoel Rishon LeZion","away":"Bnei Yehuda Tel Aviv","homeScore":"1","HomeScoreInt":1,"awayScore":"0","awayScoreInt":0},{"competition":"Premiership 22/23","home":"Rangers","away":"Celtic","homeScore":"2","HomeScoreInt":2,"awayScore":"2","awayScoreInt":2},{"competition":"Premiership 22/23","home":"Aberdeen","away":"Ross County","homeScore":"0","HomeScoreInt":0,"awayScore":"0","awayScoreInt":0},{"competition":"Premiership 22/23","home":"Hearts","away":"Hibernian","homeScore":"3","HomeScoreInt":3,"awayScore":"0","awayScoreInt":0},{"competition":"Premiership 22/23","home":"Kilmarnock","away":"St. Mirren","homeScore":"0","HomeScoreInt":0,"awayScore":"0","awayScoreInt":0},{"competition":"Premiership 22/23","home":"Livingston","away":"Motherwell","homeScore":"1","HomeScoreInt":1,"awayScore":"1","awayScoreInt":1},{"competition":"Premiership 22/23","home":"St. Johnstone","away":"Dundee United","homeScore":"0","HomeScoreInt":0,"awayScore":"1","awayScoreInt":1},{"competition":"Championship 22/23","home":"Dundee FC","away":"Arbroath","homeScore":"2","HomeScoreInt":2,"awayScore":"4","awayScoreInt":4},{"competition":"Championship 22/23","home":"Hamilton Academical","away":"Raith Rovers","homeScore":"0","HomeScoreInt":0,"awayScore":"1","awayScoreInt":1},{"competition":"Championship 22/23","home":"Inverness CT","away":"Cove Rangers","homeScore":"6","HomeScoreInt":6,"awayScore":"1","awayScoreInt":1},{"competition":"Championship 22/23","home":"Queen's Park","away":"Partick Thistle","homeScore":"2","HomeScoreInt":2,"awayScore":"0","awayScoreInt":0},{"competition":"Premier League","home":"Al-Hilal Alsahil","away":"Wad Nobawi","homeScore":"1","HomeScoreInt":1,"awayScore":"1","awayScoreInt":1},{"competition":"Premier League","home":"Ahli AL Khartoum","away":"Al Shorta","homeScore":"1","HomeScoreInt":1,"awayScore":"0","awayScoreInt":0},{"competition":"Premier League","home":"Al Hilal Omdurman","away":"Al-Zoma","homeScore":"2","HomeScoreInt":2,"awayScore":"0","awayScoreInt":0},{"competition":"Premier League","home":"Al-Merreikh","away":"Hay al-Arab","homeScore":"3","HomeScoreInt":3,"awayScore":"1","awayScoreInt":1}]