[{"competition":"Friendlies","home":"Nepal","away":"Laos","homeScore":"2","HomeScoreInt":2,"awayScore":"0","awayScoreInt":0},{"competition":"Friendlies","home":"Myanmar","away":"India","homeScore":"0","HomeScoreInt":0,"awayScore":"1","awayScoreInt":1},{"competition":"Friendlies","home":"Ireland","away":"Latvia","homeScore":"3","HomeScoreInt":3,"awayScore":"2","awayScoreInt":2},{"competition":"Quarter-Finals 22/23","home":"Olympique Lyonnais Women","away":"Chelsea Women","homeScore":"0","HomeScoreInt":0,"awayScore":"1","awayScoreInt":1},{"competition":"Quarter-Finals 22/23","home":"Paris Saint Germain Women","away":"Wolfsburg Women","homeScore":"0","HomeScoreInt":0,"awayScore":"1","awayScoreInt":1},{"competition":"Club Friendlies 2023","home":"SC Heerenveen","away":"Vitesse","homeScore":"1","HomeScoreInt":1,"awayScore":"1","awayScoreInt":1},{"competition":"Club Friendlies 2023","home":"Utsiktens BK","away":"Varbergs BoIS FC","homeScore":"2","HomeScoreInt":2,"awayScore":"0","awayScoreInt":0},{"competition":"Women's Super League: Championship","home":"Standard Liege Women","away":"Anderlecht Women","homeScore":"1","HomeScoreInt":1,"awayScore":"0","awayScoreInt":0},{"competition":"Paulista A2: Play-off","home":"Noroeste","away":"Velo Clube","homeScore":"0","HomeScoreInt":0,"awayScore":"0","awayScoreInt":0},{"competition":"Paulista A2: Play-off","home":"Novorizontino","away":"Oeste FC","homeScore":"1","HomeScoreInt":1,"awayScore":"0","awayScoreInt":0},{"competition":"Brasileiro U20: Group A","home":"Fluminense U20","away":"Internacional U20","homeScore":"0","HomeScoreInt":0,"awayScore":"0","awayScoreInt":0},{"competition":"Brasileiro U20: Group A","home":"Ceara U20","away":"Corinthians U20","homeScore":"2","HomeScoreInt":2,"awayScore":"1","awayScoreInt":1},{"competition":"Brasileiro U20: Group A","home":"Flamengo U20","away":"RB Bragantino SP U20","homeScore":"4","HomeScoreInt":4,"awayScore":"3","awayScoreInt":3},{"competition":"League 2 22/23","home":"Mansfield Town","away":"Grimsby Town","homeScore":"0","HomeScoreInt":0,"awayScore":"0","awayScoreInt":0},{"competition":"Premier League","home":"Haidob Al Nuhod","away":"Tuti","homeScore":"1","HomeScoreInt":1,"awayScore":"0","awayScoreInt":0},{"competition":"Premier League","home":"Al-Merreikh","away":"Al-Ahly Merowe","homeScore":"2","HomeScoreInt":2,"awayScore":"0","awayScoreInt":0},{"competition":"Premier League","home":"Hilal Al-Fasher","away":"Al Shorta","homeScore":"1","HomeScoreInt":1,"awayScore":"2","awayScoreInt":2}]