[{"competition":"LaLiga","home":"Celta Vigo","away":"Deportivo Alaves","homeScore":"1","HomeScoreInt":1,"awayScore":"1","awayScoreInt":1},{"competition":"LaLiga","home":"Granada","away":"Real Betis","homeScore":"1","HomeScoreInt":1,"awayScore":"1","awayScoreInt":1},{"competition":"LaLiga","home":"Osasuna","away":"Atletico Madrid","homeScore":"0","HomeScoreInt":0,"awayScore":"2","awayScoreInt":2},{"competition":"Serie A","home":"Frosinone","away":"Fiorentina","homeScore":"1","HomeScoreInt":1,"awayScore":"1","awayScoreInt":1},{"competition":"Serie A","home":"Monza","away":"Bologna","homeScore":"0","HomeScoreInt":0,"awayScore":"0","awayScoreInt":0},{"competition":"Serie A","home":"Genoa","away":"Roma","homeScore":"4","HomeScoreInt":4,"awayScore":"1","awayScoreInt":1},{"competition":"Eredivisie","home":"AZ Alkmaar","away":"Heracles","homeScore":"1","HomeScoreInt":1,"awayScore":"1","awayScoreInt":1},{"competition":"Super Lig","home":"Fenerbahce","away":"Istanbul Basaksehir","homeScore":"4","HomeScoreInt":4,"awayScore":"0","awayScoreInt":0},{"competition":"Primeira Liga","home":"CF Estrela","away":"SC Braga","homeScore":"2","HomeScoreInt":2,"awayScore":"4","awayScoreInt":4},{"competition":"Belgian Pro League","home":"RWD Molenbeek","away":"Union St.Gilloise","homeScore":"2","HomeScoreInt":2,"awayScore":"3","awayScoreInt":3},{"competition":"Belgian Pro League","home":"Club Brugge","away":"Genk","homeScore":"1","HomeScoreInt":1,"awayScore":"1","awayScoreInt":1},{"competition":"League Cup Round 3: Group A","home":"Casa Pia AC","away":"Nacional","homeScore":"2","HomeScoreInt":2,"awayScore":"1","awayScoreInt":1},{"competition":"Super League","home":"Basel","away":"Luzern","homeScore":"1","HomeScoreInt":1,"awayScore":"1","awayScoreInt":1},{"competition":"Super League","home":"FC Stade Lausanne-Ouchy","away":"Yverdon","homeScore":"1","HomeScoreInt":1,"awayScore":"1","awayScoreInt":1},{"competition":"Premier League","home":"Al Masry","away":"Pharco FC","homeScore":"1","HomeScoreInt":1,"awayScore":"0","awayScoreInt":0},{"competition":"Premier League","home":"Ismaily SC","away":"Al-Ittihad Alexandria","homeScore":"3","HomeScoreInt":3,"awayScore":"1","awayScoreInt":1},{"competition":"DBU Pokalen","home":"Kolding IF","away":"FC Nordsjaelland","homeScore":"2","HomeScoreInt":2,"awayScore":"2","awayScoreInt":2},{"competition":"DBU Pokalen","home":"Nykoebing FC","away":"AGF","homeScore":"0","HomeScoreInt":0,"awayScore":"1","awayScoreInt":1},{"competition":"Super League","home":"Asteras Tripolis","away":"Panathinaikos","homeScore":"1","HomeScoreInt":1,"awayScore":"4","awayScoreInt":4},{"competition":"Super League","home":"AEK Athens","away":"Atromitos","homeScore":"2","HomeScoreInt":2,"awayScore":"1","awayScoreInt":1},{"competition":"Cup","home":"Kalamata","away":"Athens Kallithea","homeScore":"1","HomeScoreInt":1,"awayScore":"1","awayScoreInt":1},{"competition":"Cup","home":"Mikrasiatikos","away":"Apollon Paralimniou","homeScore":"3","HomeScoreInt":3,"awayScore":"1","awayScoreInt":1},{"competition":"Ekstraklasa","home":"Lech Poznan","away":"Rakow Czestochowa","homeScore":"4","HomeScoreInt":4,"awayScore":"1","awayScoreInt":1},{"competition":"Parva Liga","home":"Etar","away":"Pirin Blagoevgrad","homeScore":"0","HomeScoreInt":0,"awayScore":"2","awayScoreInt":2},{"competition":"Parva Liga","home":"Krumovgrad","away":"Arda Kardzhali","homeScore":"1","HomeScoreInt":1,"awayScore":"3","awayScoreInt":3},{"competition":"Parva Liga","home":"PFC CSKA-Sofia","away":"PFC Lokomotiv Sofia 1929","homeScore":"2","HomeScoreInt":2,"awayScore":"0","awayScoreInt":0},{"competition":"Club Friendlies 2023","home":"Blooming","away":"Royal Pari","homeScore":"1","HomeScoreInt":1,"awayScore":"1","awayScoreInt":1},{"competition":"Campeones Cup","home":"Los Angeles FC","away":"Tigres","homeScore":"0","HomeScoreInt":0,"awayScore":"0","awayScoreInt":0},{"competition":"Central American Cup: Knockout Stage","home":"Real Esteli FC","away":"Deportivo Saprissa","homeScore":"1","HomeScoreInt":1,"awayScore":"0","awayScoreInt":0},{"competition":"Central American Cup: Knockout Stage","home":"Comunicaciones FC","away":"Club Sport Herediano","homeScore":"0","HomeScoreInt":0,"awayScore":"0","awayScoreInt":0},{"competition":"Kategoria Superiore","home":"Laci","away":"FC Dinamo City","homeScore":"0","HomeScoreInt":0,"awayScore":"1","awayScoreInt":1},{"competition":"Kategoria e Pare","home":"Apolonia","away":"Burreli","homeScore":"3","HomeScoreInt":3,"awayScore":"0","awayScoreInt":0},{"competition":"Kategoria e Pare","home":"FK Vora","away":"FK Tomori Berat","homeScore":"5","HomeScoreInt":5,"awayScore":"1","awayScoreInt":1},{"competition":"Kategoria e Pare","home":"KF Bylis","away":"KS Korabi","homeScore":"1","HomeScoreInt":1,"awayScore":"0","awayScoreInt":0},{"competition":"Kategoria e Pare","home":"KS Besa Kavaje","away":"AF Elbasani","homeScore":"0","HomeScoreInt":0,"awayScore":"1","awayScoreInt":1},{"competition":"Kategoria e Pare","home":"KS Lushnja","away":"Flamurtari FC","homeScore":"0","HomeScoreInt":0,"awayScore":"4","awayScoreInt":4},{"competition":"Ligue 1 U21","home":"ASO Chlef U21","away":"CS Constantine U21","homeScore":"1","HomeScoreInt":1,"awayScore":"0","awayScoreInt":0},{"competition":"Ligue 1 U21","home":"ES Setif U21","away":"USM Alger U21","homeScore":"3","HomeScoreInt":3,"awayScore":"0","awayScoreInt":0},{"competition":"Ligue 1 U21","home":"JS Saoura U21","away":"Ben Aknoun U21","homeScore":"1","HomeScoreInt":1,"awayScore":"0","awayScoreInt":0},{"competition":"Ligue 1 U21","home":"MC Alger U21","away":"MC El Bayadh U21","homeScore":"1","HomeScoreInt":1,"awayScore":"0","awayScoreInt":0},{"competition":"Ligue 1 U21","home":"NC Magra U21","away":"US Biskra U21","homeScore":"2","HomeScoreInt":2,"awayScore":"1","awayScoreInt":1},{"competition":"Ligue 1 U21","home":"Paradou AC U21","away":"CR Belouizdad U21","homeScore":"3","HomeScoreInt":3,"awayScore":"2","awayScoreInt":2},{"competition":"Ligue 1 U21","home":"US Souf U21","away":"MC Oran U21","homeScore":"1","HomeScoreInt":1,"awayScore":"0","awayScoreInt":0},{"competition":"Ligue 1 U21","home":"USM Khenchela U21","away":"JS Kabylie U21","homeScore":"0","HomeScoreInt":0,"awayScore":"1","awayScoreInt":1},{"competition":"Premier League","home":"Urartu FC","away":"BKMA","homeScore":"2","HomeScoreInt":2,"awayScore":"1","awayScoreInt":1},{"competition":"Women's Asian Games: Group A","home":"Uzbekistan Women","away":"China Women","homeScore":"0","HomeScoreInt":0,"awayScore":"6","awayScoreInt":6},{"competition":"Women's Asian Games: Group D","home":"Japan Women","away":"Vietnam Women","homeScore":"7","HomeScoreInt":7,"awayScore":"0","awayScoreInt":0},{"competition":"Women's Asian Games: Group D","home":"Nepal Women","away":"Bangladesh Women","homeScore":"1","HomeScoreInt":1,"awayScore":"1","awayScoreInt":1},{"competition":"Women's Asian Games: Group E","home":"Philippines Women","away":"Myanmar Women","homeScore":"3","HomeScoreInt":3,"awayScore":"0","awayScoreInt":0},{"competition":"Women's Asian Games: Group E","home":"South Korea Women","away":"Hong Kong Women","homeScore":"5","HomeScoreInt":5,"awayScore":"0","awayScoreInt":0},{"competition":"Asian Games U23: Round of 16","home":"Uzbekistan U23","away":"Indonesia U23","homeScore":"2","HomeScoreInt":2,"awayScore":"0","awayScoreInt":0},{"competition":"Asian Games U23: Round of 16","home":"India U23","away":"Saudi Arabia U23","homeScore":"0","HomeScoreInt":0,"awayScore":"2","awayScoreInt":2},{"competition":"Asian Games U23: Round of 16","home":"Japan U23","away":"Myanmar U23","homeScore":"7","HomeScoreInt":7,"awayScore":"0","awayScoreInt":0},{"competition":"1st Division","home":"PFK Zaqatala","away":"Moik Baku","homeScore":"2","HomeScoreInt":2,"awayScore":"2","awayScoreInt":2},{"competition":"1st Division","home":"Imisli FK","away":"Shamakhi FK","homeScore":"0","HomeScoreInt":0,"awayScore":"3","awayScoreInt":3},{"competition":"Premier League","home":"Al-Najma","away":"Al-Shabab","homeScore":"3","HomeScoreInt":3,"awayScore":"2","awayScoreInt":2},{"competition":"Premier League","home":"Manama","away":"Al-Hala","homeScore":"1","HomeScoreInt":1,"awayScore":"2","awayScoreInt":2},{"competition":"Cup","home":"Sloboda Tuzla","away":"Zeljeznicar","homeScore":"1","HomeScoreInt":1,"awayScore":"0","awayScoreInt":0},{"competition":"Gaucho Serie B: Group B","home":"Riopardense RS","away":"Real SC Tramandai RS","homeScore":"3","HomeScoreInt":3,"awayScore":"1","awayScoreInt":1},{"competition":"Gaucho Serie B: Group D","home":"Sao Paulo RS","away":"FC Riograndense","homeScore":"2","HomeScoreInt":2,"awayScore":"3","awayScoreInt":3},{"competition":"Women's Gaucho","home":"Gremio Women","away":"SC Internacional RS Women","homeScore":"2","HomeScoreInt":2,"awayScore":"1","awayScoreInt":1},{"competition":"Vtora Liga","home":"Dobrudzha Dobrich","away":"Spartak Varna","homeScore":"2","HomeScoreInt":2,"awayScore":"0","awayScoreInt":0},{"competition":"Vtora Liga","home":"Ludogorets Razgrad II","away":"Sportist Svoge","homeScore":"3","HomeScoreInt":3,"awayScore":"1","awayScoreInt":1},{"competition":"Vtora Liga","home":"Septemvri Sofia","away":"Maritsa Plovdiv","homeScore":"3","HomeScoreInt":3,"awayScore":"1","awayScoreInt":1},{"competition":"Copa Chile","home":"Universidad de Concepcion","away":"Magallanes","homeScore":"1","HomeScoreInt":1,"awayScore":"3","awayScoreInt":3},{"competition":"Caribbean Club Championship: Group A","home":"AC Port of Spain","away":"Defence Force","homeScore":"1","HomeScoreInt":1,"awayScore":"1","awayScoreInt":1},{"competition":"Caribbean Club Championship: Group B","home":"Harbour View","away":"S.V. Robinhood","homeScore":"3","HomeScoreInt":3,"awayScore":"2","awayScoreInt":2},{"competition":"Divize D","home":"TJ Sokol Lanzhot","away":"AFC Humpolec","homeScore":"4","HomeScoreInt":4,"awayScore":"1","awayScoreInt":1},{"competition":"Divize E","home":"FC Strani","away":"FK Kozlovice","homeScore":"2","HomeScoreInt":2,"awayScore":"0","awayScoreInt":0},{"competition":"Divize F","home":"Vratimov","away":"Bridlicna","homeScore":"3","HomeScoreInt":3,"awayScore":"0","awayScoreInt":0},{"competition":"U19 League","home":"Ceske Budejovice U19","away":"MFK Frydek Mistek U19","homeScore":"6","HomeScoreInt":6,"awayScore":"1","awayScoreInt":1},{"competition":"Primera Division: Apertura","home":"CD FAS","away":"CD Dragon","homeScore":"1","HomeScoreInt":1,"awayScore":"0","awayScoreInt":0},{"competition":"Primera Division U20: Apertura","home":"Santa Tecla FC U20","away":"Jocoro FC U20","homeScore":"7","HomeScoreInt":7,"awayScore":"1","awayScoreInt":1},{"competition":"Premier League International Cup: Group A","home":"Leeds United U21","away":"Nice U23","homeScore":"2","HomeScoreInt":2,"awayScore":"0","awayScoreInt":0},{"competition":"Regionalliga Bayern","home":"Turkgucu Munchen","away":"Wurzburger Kickers","homeScore":"0","HomeScoreInt":0,"awayScore":"1","awayScoreInt":1},{"competition":"National League","home":"St Joseph's","away":"Lincoln Red Imps FC","homeScore":"1","HomeScoreInt":1,"awayScore":"0","awayScoreInt":0},{"competition":"NB II","home":"Budapest Honved","away":"Budafok","homeScore":"2","HomeScoreInt":2,"awayScore":"2","awayScoreInt":2},{"competition":"Super League","home":"Odisha FC","away":"Mumbai City FC","homeScore":"2","HomeScoreInt":2,"awayScore":"2","awayScoreInt":2},{"competition":"Liga Leumit","home":"Bnei Yehuda Tel Aviv","away":"Maccabi Herzliya","homeScore":"3","HomeScoreInt":3,"awayScore":"0","awayScoreInt":0},{"competition":"Liga Leumit","home":"Hapoel Nir Ramat HaSharon","away":"Sektzia Nes Tziona","homeScore":"5","HomeScoreInt":5,"awayScore":"2","awayScoreInt":2},{"competition":"Liga Leumit","home":"Hapoel Nof HaGalil","away":"Hapoel Ironi Kiryat Shmona","homeScore":"2","HomeScoreInt":2,"awayScore":"1","awayScoreInt":1},{"competition":"Liga Leumit","home":"Hapoel Rishon LeZion","away":"Hapoel Umm al-Fahm","homeScore":"1","HomeScoreInt":1,"awayScore":"1","awayScoreInt":1},{"competition":"Liga Leumit","home":"Ihud Bnei Shefa-Amr","away":"Hapoel Kfar Saba","homeScore":"1","HomeScoreInt":1,"awayScore":"2","awayScoreInt":2},{"competition":"Liga Alef: North","home":"Hapoel Bueine","away":"Hapoel Kafr Kanna","homeScore":"2","HomeScoreInt":2,"awayScore":"2","awayScoreInt":2},{"competition":"Liga Alef: North","home":"Hapoel Kaukab","away":"MS Football Hapoel Kiryat Yam","homeScore":"3","HomeScoreInt":3,"awayScore":"4","awayScoreInt":4},{"competition":"Liga Alef: North","home":"Hapoel Migdal Haemeq","away":"MS Tira","homeScore":"1","HomeScoreInt":1,"awayScore":"2","awayScoreInt":2},{"competition":"Liga Alef: North","home":"Maccabi Ahi Nazareth","away":"SC Tzeirey Taibe","homeScore":"2","HomeScoreInt":2,"awayScore":"1","awayScoreInt":1},{"competition":"Liga Alef: North","home":"Ironi Nesher","away":"Baqa Al-Gharbiyye","homeScore":"0","HomeScoreInt":0,"awayScore":"0","awayScoreInt":0},{"competition":"Liga Alef: North","home":"Tzeirey Um El Fahem","away":"Hapoel Bnei Zalafa","homeScore":"0","HomeScoreInt":0,"awayScore":"1","awayScoreInt":1},{"competition":"Liga Alef: South","home":"Maccabi Shaaraim","away":"Hapoel Herzelia","homeScore":"3","HomeScoreInt":3,"awayScore":"2","awayScoreInt":2},{"competition":"Liga Alef: South","home":"AS Nordia Jerusalem","away":"Hapoel Bikat Hayarden","homeScore":"3","HomeScoreInt":3,"awayScore":"1","awayScoreInt":1},{"competition":"Liga Alef: South","home":"Ironi Modiin","away":"Hapoel Marmorek","homeScore":"3","HomeScoreInt":3,"awayScore":"1","awayScoreInt":1},{"competition":"Liga Alef: South","home":"Hapoel Kfar Shalem","away":"Shimshon Kafr Qasim","homeScore":"2","HomeScoreInt":2,"awayScore":"0","awayScoreInt":0},{"competition":"Liga Alef: South","home":"SC Hapoel Lod","away":"FC Holon Yermiyahu","homeScore":"2","HomeScoreInt":2,"awayScore":"2","awayScoreInt":2},{"competition":"Liga Alef: South","home":"Maccabi Ironi Ashdod FC","away":"Agudat Sport Ashdod","homeScore":"1","HomeScoreInt":1,"awayScore":"2","awayScoreInt":2},{"competition":"Cup","home":"Al-Salt","away":"Al-Arabi","homeScore":"2","HomeScoreInt":2,"awayScore":"1","awayScoreInt":1},{"competition":"Cup","home":"Mgaear Al Sarhan","away":"Sama","homeScore":"0","HomeScoreInt":0,"awayScore":"0","awayScoreInt":0},{"competition":"Cup","home":"Al-Jalil","away":"Dogra","homeScore":"2","HomeScoreInt":2,"awayScore":"2","awayScoreInt":2},{"competition":"Cup","home":"Al-Wehdat","away":"Jerash","homeScore":"2","HomeScoreInt":2,"awayScore":"0","awayScoreInt":0},{"competition":"Superleague","home":"FC Prishtina","away":"Dukagjini","homeScore":"2","HomeScoreInt":2,"awayScore":"2","awayScoreInt":2},{"competition":"Superleague","home":"Feronikeli","away":"Drita","homeScore":"0","HomeScoreInt":0,"awayScore":"2","awayScoreInt":2},{"competition":"Premier League","home":"Al-Ansar","away":"Al-Ahed","homeScore":"1","HomeScoreInt":1,"awayScore":"1","awayScoreInt":1},{"competition":"Premier League","home":"Racing Beirut","away":"Al-Nejmeh","homeScore":"1","HomeScoreInt":1,"awayScore":"1","awayScoreInt":1},{"competition":"A Lyga","home":"FK Kauno Zalgiris","away":"Dainava Alytus","homeScore":"1","HomeScoreInt":1,"awayScore":"1","awayScoreInt":1},{"competition":"Liga de Expansion MX: Apertura","home":"Alebrijes Oaxaca","away":"Dorados","homeScore":"4","HomeScoreInt":4,"awayScore":"0","awayScoreInt":0},{"competition":"Liga de Expansion MX: Apertura","home":"Venados FC","away":"CD Tepatitlan de Morelos","homeScore":"5","HomeScoreInt":5,"awayScore":"1","awayScoreInt":1},{"competition":"Liga de Expansion MX: Apertura","home":"Celaya","away":"Cancun FC","homeScore":"1","HomeScoreInt":1,"awayScore":"0","awayScoreInt":0},{"competition":"Liga MX U23: Apertura","home":"Atlas U23","away":"Puebla U23","homeScore":"3","HomeScoreInt":3,"awayScore":"0","awayScoreInt":0},{"competition":"Liga Primera: Apertura","home":"Deportivo Ocotal","away":"Managua FC","homeScore":"3","HomeScoreInt":3,"awayScore":"2","awayScoreInt":2},{"competition":"Liga Primera: Apertura","home":"Masachapa FC","away":"Diriangen FC","homeScore":"2","HomeScoreInt":2,"awayScore":"1","awayScoreInt":1},{"competition":"NM Cup: Semi-Finals","home":"Vaalerenga","away":"Bodo/Glimt","homeScore":"2","HomeScoreInt":2,"awayScore":"4","awayScoreInt":4},{"competition":"Professional League","home":"Oman FC","away":"Al-Nasr Salalah","homeScore":"1","HomeScoreInt":1,"awayScore":"0","awayScoreInt":0},{"competition":"Professional League","home":"Sur","away":"Bahla","homeScore":"2","HomeScoreInt":2,"awayScore":"0","awayScoreInt":0},{"competition":"Liga 1: Clausura","home":"Union Comercio","away":"Binacional","homeScore":"2","HomeScoreInt":2,"awayScore":"2","awayScoreInt":2},{"competition":"Cup","home":"Pogon Szczecin II","away":"Polonia Bytom","homeScore":"1","HomeScoreInt":1,"awayScore":"4","awayScoreInt":4},{"competition":"Cup","home":"GKS Tychy 71","away":"Wisla Plock","homeScore":"3","HomeScoreInt":3,"awayScore":"1","awayScoreInt":1},{"competition":"Cup","home":"Kotwica Kolobrzeg","away":"Termalica Nieciecza","homeScore":"4","HomeScoreInt":4,"awayScore":"4","awayScoreInt":4},{"competition":"Cup","home":"Wisla Krakow","away":"Lechia Gdansk","homeScore":"2","HomeScoreInt":2,"awayScore":"1","awayScoreInt":1},{"competition":"Qatar Stars League","home":"Al-Sadd","away":"Al-Gharafa","homeScore":"4","HomeScoreInt":4,"awayScore":"0","awayScoreInt":0},{"competition":"Qatar Stars League","home":"Al Markhiya","away":"Al-Duhail SC","homeScore":"1","HomeScoreInt":1,"awayScore":"2","awayScoreInt":2},{"competition":"Qatar Stars League","home":"Al-Arabi","away":"Qatar SC","homeScore":"1","HomeScoreInt":1,"awayScore":"0","awayScoreInt":0},{"competition":"Romanian Cup: Group B","home":"Steaua Bucuresti","away":"Universitatea Cluj","homeScore":"1","HomeScoreInt":1,"awayScore":"3","awayScoreInt":3},{"competition":"Romanian Cup: Group B","home":"CSM Alexandria","away":"CFR Cluj","homeScore":"1","HomeScoreInt":1,"awayScore":"3","awayScoreInt":3},{"competition":"Romanian Cup: Group B","home":"Botosani","away":"FC Rapid 1923","homeScore":"1","HomeScoreInt":1,"awayScore":"3","awayScoreInt":3},{"competition":"Coppa Titano","home":"Folgore","away":"SS Pennarossa","homeScore":"1","HomeScoreInt":1,"awayScore":"0","awayScoreInt":0},{"competition":"Coppa Titano","home":"S.S. Murata","away":"Domagnano","homeScore":"0","HomeScoreInt":0,"awayScore":"0","awayScoreInt":0},{"competition":"Prva Liga","home":"Maribor","away":"Radomlje","homeScore":"3","HomeScoreInt":3,"awayScore":"1","awayScoreInt":1},{"competition":"Prva Liga","home":"Olimpija Ljubljana","away":"Koper","homeScore":"1","HomeScoreInt":1,"awayScore":"1","awayScoreInt":1},{"competition":"Tercera RFEF: Group 10","home":"AD Cartaya","away":"Cordoba CF B","homeScore":"1","HomeScoreInt":1,"awayScore":"1","awayScoreInt":1},{"competition":"Turkiye Cup: Round 1","home":"Arguvan Belediyespor","away":"Elazigspor","homeScore":"2","HomeScoreInt":2,"awayScore":"1","awayScoreInt":1},{"competition":"Premier League","home":"Bright Stars FC","away":"URA FC","homeScore":"1","HomeScoreInt":1,"awayScore":"1","awayScoreInt":1},{"competition":"Premier League","home":"Busoga United FC","away":"Express FC","homeScore":"0","HomeScoreInt":0,"awayScore":"2","awayScoreInt":2},{"competition":"Pro League","home":"Hatta","away":"Al-Nasr SC","homeScore":"0","HomeScoreInt":0,"awayScore":"3","awayScoreInt":3},{"competition":"Pro League","home":"Sharjah Cultural Club","away":"Al-Ain","homeScore":"2","HomeScoreInt":2,"awayScore":"3","awayScoreInt":3},{"competition":"MLS 2023","home":"Philadelphia Union","away":"FC Dallas","homeScore":"1","HomeScoreInt":1,"awayScore":"1","awayScoreInt":1},{"competition":"MLS 2023","home":"Colorado Rapids","away":"Vancouver Whitecaps","homeScore":"2","HomeScoreInt":2,"awayScore":"2","awayScoreInt":2},{"competition":"Semi Finals","home":"Fluminense","away":"Internacional","homeScore":"2","HomeScoreInt":2,"awayScore":"2","awayScoreInt":2}]